pydantic_scrape/__init__.py
pydantic_scrape/agents/__init__.py
pydantic_scrape/agents/browse_agent.py
pydantic_scrape/agents/browse_agent_with_extensions.py
pydantic_scrape/agents/bs4_scrape_script_agent.py
pydantic_scrape/agents/chawan_browse_agent.py
pydantic_scrape/agents/clean_scrape_agent.py
pydantic_scrape/agents/curl_browse_agent.py
pydantic_scrape/agents/flexible_scrape_agent.py
pydantic_scrape/agents/scalable_tab_agent.py
pydantic_scrape/agents/scrape.py
pydantic_scrape/agents/search.py
pydantic_scrape/agents/search_and_browse.py
pydantic_scrape/agents/search_and_browse_singular.py
pydantic_scrape/agents/summarization.py
pydantic_scrape/agents/tab_session_agent.py
pydantic_scrape/agents/youtube_director_gemini.py
pydantic_scrape/dependencies/__init__.py
pydantic_scrape/dependencies/ai_scraper.py
pydantic_scrape/dependencies/article.py
pydantic_scrape/dependencies/batch_scraping.py
pydantic_scrape/dependencies/chawan_browser_api.py
pydantic_scrape/dependencies/chawan_subprocess_api.py
pydantic_scrape/dependencies/content_analysis.py
pydantic_scrape/dependencies/crossref.py
pydantic_scrape/dependencies/document.py
pydantic_scrape/dependencies/fetch.py
pydantic_scrape/dependencies/google_search.py
pydantic_scrape/dependencies/openalex.py
pydantic_scrape/dependencies/script_generator.py
pydantic_scrape/graphs/__init__.py
pydantic_scrape/graphs/davinci_importer.py
pydantic_scrape/graphs/dynamic_scrape.py
pydantic_scrape/graphs/edl_exporter.py
pydantic_scrape/graphs/full_scrape_graph.py
pydantic_scrape/graphs/google_search_scrape_answer.py
pydantic_scrape/graphs/search_answer.py
pydantic_scrape/graphs/search_scrape_answer.py
pydantic_scrape/graphs/xml_exporter.py
pydantic_scrape/graphs/youtube_editor.py
pydantic_scrape/mcp/__init__.py
pydantic_scrape/mcp/camoufox_mcp_server.py
pydantic_scrape/services/__init__.py
pydantic_scrape/services/download_service.py
pydantic_scrape/services/transcription_service.py
pydantic_scrape/toolsets/agent_toolset.py
pydantic_scrape-0.2.2.dist-info/METADATA
pydantic_scrape-0.2.2.dist-info/WHEEL
pydantic_scrape-0.2.2.dist-info/top_level.txt
pydantic_scrape-0.2.2.dist-info/RECORD
