Metadata-Version: 2.4
Name: pydantic-scrape
Version: 0.2.2
Summary: Advanced web automation framework with AI-powered agents, Chawan terminal browser integration, and geographic search targeting
Author: Pydantic Scrape Contributors
License: MIT
Project-URL: Homepage, https://github.com/philmade/pydantic_scrape
Project-URL: Repository, https://github.com/philmade/pydantic_scrape
Project-URL: Issues, https://github.com/philmade/pydantic_scrape/issues
Keywords: scraping,web-scraping,pydantic,chawan,automation,browser-automation,ai-agents,geographic-search
Classifier: Development Status :: 3 - Alpha
Classifier: Intended Audience :: Developers
Classifier: License :: OSI Approved :: MIT License
Classifier: Programming Language :: Python :: 3
Classifier: Programming Language :: Python :: 3.10
Classifier: Programming Language :: Python :: 3.11
Classifier: Programming Language :: Python :: 3.12
Classifier: Topic :: Internet :: WWW/HTTP :: Browsers
Classifier: Topic :: Software Development :: Libraries :: Python Modules
Classifier: Topic :: Text Processing :: Markup :: HTML
Requires-Python: >=3.10
Requires-Dist: pydantic-ai>=0.2.11
Requires-Dist: pydantic-graph>=0.2.11
Requires-Dist: loguru>=0.7.3
Requires-Dist: python-dotenv
Requires-Dist: httpx>=0.24.0
Requires-Dist: platformdirs>=3.0.0
Requires-Dist: beautifulsoup4>=4.13.0
Requires-Dist: lxml>=4.9.0
Requires-Dist: lxml_html_clean>=0.1.0
Requires-Dist: rapidfuzz
Provides-Extra: youtube
Requires-Dist: yt-dlp>=2023.12.30; extra == "youtube"
Provides-Extra: ai
Requires-Dist: openai>=1.0.0; extra == "ai"
Requires-Dist: google-generativeai>=0.3.0; extra == "ai"
Provides-Extra: academic
Requires-Dist: pyalex>=0.17; extra == "academic"
Requires-Dist: habanero>=1.2.6; extra == "academic"
Provides-Extra: documents
Requires-Dist: PyMuPDF>=1.25.0; extra == "documents"
Requires-Dist: python-docx>=1.1.0; extra == "documents"
Requires-Dist: EbookLib>=0.19; extra == "documents"
Provides-Extra: content
Requires-Dist: goose3>=3.1.19; extra == "content"
Requires-Dist: newspaper3k>=0.2.8; extra == "content"
Provides-Extra: camoufox
Requires-Dist: camoufox>=0.4.11; extra == "camoufox"
Provides-Extra: all
Requires-Dist: yt-dlp>=2023.12.30; extra == "all"
Requires-Dist: openai>=1.0.0; extra == "all"
Requires-Dist: google-generativeai>=0.3.0; extra == "all"
Requires-Dist: pyalex>=0.17; extra == "all"
Requires-Dist: habanero>=1.2.6; extra == "all"
Requires-Dist: PyMuPDF>=1.25.0; extra == "all"
Requires-Dist: python-docx>=1.1.0; extra == "all"
Requires-Dist: EbookLib>=0.19; extra == "all"
Requires-Dist: goose3>=3.1.19; extra == "all"
Requires-Dist: newspaper3k>=0.2.8; extra == "all"
Requires-Dist: camoufox>=0.4.11; extra == "all"
Provides-Extra: dev
Requires-Dist: pytest>=7.4.0; extra == "dev"
Requires-Dist: pytest-asyncio>=0.21.0; extra == "dev"
Requires-Dist: black>=23.0.0; extra == "dev"
Requires-Dist: ruff>=0.1.0; extra == "dev"
Requires-Dist: build>=1.0.0; extra == "dev"
Requires-Dist: twine>=4.0.0; extra == "dev"
